 [
        {
            "name": "Avinash",
            "location": "Gurgaon",
            "email": "avinash.r@prodpat.com",
            "phone": "+918824258781"
        },
        {
            "name": "Rajdeep",
            "location": "Bengalore",
            "email": "rajdeep@prodpat.com",
            "phone": "+918824258781"
        },
        {
            "name": "Deb",
            "location": "Chennai",
            "email": "debabatra.b@prodpat.com",
            "phone": "+918824258781"
        },
        {
            "name": "Anjali",
            "location": "Bengalore",
            "email": "anjali.a@prodpat.com",
            "phone": "+918824258781"
        }
    ]